README.md
setup.cfg
setup.py
mklaren/__init__.py
mklaren.egg-info/PKG-INFO
mklaren.egg-info/SOURCES.txt
mklaren.egg-info/dependency_links.txt
mklaren.egg-info/requires.txt
mklaren.egg-info/top_level.txt
mklaren/kernel/__init__.py
mklaren/kernel/kernel.py
mklaren/kernel/kinterface.py
mklaren/kernel/string_kernel.py
mklaren/kernel/string_util.py
mklaren/mkl/__init__.py
mklaren/mkl/align.py
mklaren/mkl/align_csi.py
mklaren/mkl/alignf.py
mklaren/mkl/kmp.py
mklaren/mkl/l2krr.py
mklaren/mkl/mklaren.py
mklaren/mkl/uniform.py
mklaren/projection/__init__.py
mklaren/projection/csi.py
mklaren/projection/icd.py
mklaren/projection/nystrom.py
mklaren/projection/rff.py
mklaren/regression/__init__.py
mklaren/regression/ridge.py
mklaren/regression/spgp.py
mklaren/util/__init__.py
mklaren/util/la.py