Metadata-Version: 1.1
Name: mklaren
Version: 1.2
Summary: The Multiple Kernel Learning Python Library.
Home-page: https://github.com/mstrazar/mklaren
Author: Martin Strazar
Author-email: martin.strazar@gmail.com
License: UNKNOWN
Download-URL: https://github.com/mstrazar/mklaren/archive/1.1.tar.gz
Keywords: machine learning,kernel methods,low-rank approximation,regression
Platform: UNKNOWN
